napari_segment/__init__.py
napari_segment/_reader.py
napari_segment/_sample_data.py
napari_segment/_version.py
napari_segment/_widget.py
napari_segment/_writer.py
napari_segment/napari.yaml
napari_segment/_tests/__init__.py
napari_segment/_tests/test_reader.py
napari_segment/_tests/test_sample_data.py
napari_segment/_tests/test_widget.py
napari_segment/_tests/test_writer.py
napari_segment-0.3.12.dist-info/LICENSE
napari_segment-0.3.12.dist-info/METADATA
napari_segment-0.3.12.dist-info/WHEEL
napari_segment-0.3.12.dist-info/entry_points.txt
napari_segment-0.3.12.dist-info/top_level.txt
napari_segment-0.3.12.dist-info/RECORD
