Metadata-Version: 2.1
Name: napari-segment
Version: 0.3.12
Summary: Segment organoids and measure intensities
Home-page: https://github.com/aaristov/napari-segment
Author: Andrey Aristov
Author-email: aaristov@pasteur.fr
License: BSD-3-Clause
Project-URL: Bug Tracker, https://github.com/aaristov/napari-segment/issues
Project-URL: Documentation, https://github.com/aaristov/napari-segment#README.md
Project-URL: Source Code, https://github.com/aaristov/napari-segment
Project-URL: User Support, https://github.com/aaristov/napari-segment/issues
Classifier: Development Status :: 2 - Pre-Alpha
Classifier: Framework :: napari
Classifier: Intended Audience :: Developers
Classifier: License :: OSI Approved :: BSD License
Classifier: Operating System :: OS Independent
Classifier: Programming Language :: Python
Classifier: Programming Language :: Python :: 3
Classifier: Programming Language :: Python :: 3 :: Only
Classifier: Programming Language :: Python :: 3.8
Classifier: Programming Language :: Python :: 3.9
Classifier: Programming Language :: Python :: 3.10
Classifier: Topic :: Software Development :: Testing
Requires-Python: >=3.8
License-File: LICENSE
Requires-Dist: dask
Requires-Dist: imageio-ffmpeg
Requires-Dist: matplotlib
Requires-Dist: napari
Requires-Dist: nd2
Requires-Dist: numpy
Requires-Dist: pytest-qt
Requires-Dist: scikit-image
Requires-Dist: zarr
